example/__init__.py
example/blog_admin.py
example/blog_cache.py
example/blog_dynamodb.py
example/blog_gcdatastore.py
example/blog_plugins.py
example/blog_roles.py
example/main.py
example/plugins/__init__.py
example/plugins/add_view/__init__.py
example/plugins/similar_posts/__init__.py
example/plugins/tag_cloud/__init__.py
flask_blogging/__init__.py
flask_blogging/dynamodbstorage.py
flask_blogging/engine.py
flask_blogging/forms.py
flask_blogging/gcdatastore.py
flask_blogging/processor.py
flask_blogging/signals.py
flask_blogging/sqlastorage.py
flask_blogging/storage.py
flask_blogging/utils.py
flask_blogging/views.py
flask_blogging/templates/blogging/analytics.html
flask_blogging/templates/blogging/base.html
flask_blogging/templates/blogging/disqus.html
flask_blogging/templates/blogging/editor.html
flask_blogging/templates/blogging/index.html
flask_blogging/templates/blogging/metatags.html
flask_blogging/templates/blogging/page.html
flask_blogging/templates/blogging/sitemap.xml
flask_blogging/templates/blogging/social_links.html
flask_blogging/templates/fileupload/base.html
test/__init__.py
test/plugin.py
test/test_core.py
test/test_dynamodb.py
test/test_gcdatastore.py
test/test_signals.py
test/test_sqlastorage.py
test/test_views.py
test/utils.py
GC_Flask_Blogging-1.1.2.dist-info/LICENSE
GC_Flask_Blogging-1.1.2.dist-info/METADATA
GC_Flask_Blogging-1.1.2.dist-info/WHEEL
GC_Flask_Blogging-1.1.2.dist-info/top_level.txt
GC_Flask_Blogging-1.1.2.dist-info/RECORD
