Metadata-Version: 2.1
Name: GC-Flask-Blogging
Version: 1.1.2
Summary: A flask extension for adding Markdown blog support to your site
Home-page: https://github.com/gouthambs/Flask-Blogging
Author: Gouthaman Balaraman
Author-email: gouthaman.balaraman@gmail.com
License: MIT
Platform: any
Classifier: Development Status :: 4 - Beta
Classifier: Environment :: Web Environment
Classifier: Framework :: Flask
Classifier: Intended Audience :: Developers
Classifier: License :: OSI Approved :: MIT License
Classifier: Operating System :: OS Independent
Classifier: Programming Language :: Python
Classifier: Programming Language :: Python :: 2
Classifier: Programming Language :: Python :: 2.7
Classifier: Programming Language :: Python :: 3
Classifier: Programming Language :: Python :: 3.4
Classifier: Programming Language :: Python :: 3.5
Classifier: Programming Language :: Python :: 3.6
Classifier: Topic :: Internet :: WWW/HTTP :: Dynamic Content
Classifier: Topic :: Software Development :: Libraries :: Python Modules
Requires-Dist: Flask
Requires-Dist: Flask-WTF (>=0.14.0)
Requires-Dist: Flask-Login
Requires-Dist: Flask-Principal
Requires-Dist: flask-caching
Requires-Dist: GC-Flask-FileUpload
Requires-Dist: SQLAlchemy (>=0.9.1)
Requires-Dist: Markdown
Requires-Dist: Werkzeug
Requires-Dist: blinker
Requires-Dist: python-slugify
Requires-Dist: shortuuid
